<?xml version="1.0" encoding="UTF-8"?>
<root xmlns:fse="de.homelab.madgaksha.lotsofbs.tool.fancysceneeditor.view"
	xmlns:s2ui="com.badlogic.gdx.scenes.scene2d.ui">
	<s2ui:table debug fillParent>
		<s2ui:cell expand fill>
			<s2ui:splitPane>
				<s2ui:splitPane>
					<s2ui:table debug transform id="previewTable">
						<fse:preview expand fill></fse:preview>
						<s2ui:row/>
						<s2ui:table>
						    <s2ui:cell><fse:FpsInput></fse:FpsInput></s2ui:cell>
						    <s2ui:cell><fse:BeginningEndButton beginning="false"></fse:BeginningEndButton></s2ui:cell>
						    <s2ui:cell><fse:FrameSeekButton forward="false"></fse:FrameSeekButton></s2ui:cell>
						    <s2ui:cell><fse:PlayPauseButton></fse:PlayPauseButton></s2ui:cell>
						    <s2ui:cell><fse:FrameSeekButton forward="true"></fse:FrameSeekButton></s2ui:cell>
						    <s2ui:cell><fse:BeginningEndButton beginning="false"></fse:BeginningEndButton></s2ui:cell>
						    <s2ui:cell><fse:FrameCountInput></fse:FrameCountInput>
						</s2ui:table>
					</s2ui:table>
				</s2ui:splitPane>
				<fse:detailsWindow id="eventDetails"></fse:detailsWindow>
			</s2ui:splitPane>
		</s2ui:cell>
	</s2ui:table>
</root>